olxbrasil/__init__.py
olxbrasil/constants.py
olxbrasil/exceptions.py
olxbrasil/filters.py
olxbrasil/parsers/__init__.py
olxbrasil/parsers/base.py
olxbrasil/parsers/item_parser.py
olxbrasil/parsers/list_parser.py
olxbrasil/service.py
olxbrasil/utils.py
olxbrasil-0.2.7.dist-info/WHEEL
olxbrasil-0.2.7.dist-info/METADATA
olxbrasil-0.2.7.dist-info/RECORD
