Metadata-Version: 2.1
Name: olxbrasil
Version: 0.2.7
Summary: Biblioteca para scrapping da Olx Brasil (olx.com.br)
Home-page: https://github.com/Mdslino/olxbrasil
License: MIT
Keywords: scrapping,olx
Author: Marcelo Lino
Author-email: mdslino@gmail.com
Maintainer: Marcelo Lino
Maintainer-email: mdslino@gmail.com
Requires-Python: >=3.8,<4.0
Classifier: Development Status :: 4 - Beta
Classifier: Framework :: AsyncIO
Classifier: License :: OSI Approved :: MIT License
Classifier: Natural Language :: Portuguese (Brazilian)
Classifier: Operating System :: MacOS
Classifier: Operating System :: POSIX :: Linux
Classifier: Programming Language :: Python :: 3
Classifier: Programming Language :: Python :: 3.10
Classifier: Programming Language :: Python :: 3.7
Classifier: Programming Language :: Python :: 3.8
Classifier: Programming Language :: Python :: 3.9
Classifier: Programming Language :: Python :: Implementation :: CPython
Classifier: Topic :: Software Development :: Libraries
Requires-Dist: beautifulsoup4 (>=4.9.3,<5.0.0)
Requires-Dist: fake-useragent (>=0.1.11,<0.2.0)
Requires-Dist: httpx (>=0.22.0,<0.23.0)
Project-URL: Repository, https://github.com/Mdslino/olxbrasil
